[
  {
    "id": 100,
    "title": "Example Theme 1",
    "version": "1.0",
    "layouts": "Responsive, Fluid",
    "published": "January 29, 2013",
    "updated": "January 29, 2013",
    "size": "4 MB",
    "file-types": "CSS, LESS, HTML, JavaScript",
    "description": "This is a theme from example data.",
    "stats": [
      {
        "label": "purchases",
        "value": "1,250"
      },
      {
        "label": "likes",
        "value": "9,350"
      },
      {
        "label": "follows",
        "value": "850,334"
      }
    ]
  },
  {
    "id": 200,
    "title": "Example Theme 2",
    "version": "1.0",
    "layouts": "Responsive, Fluid",
    "published": "January 29, 2013",
    "updated": "January 29, 2013",
    "size": "4 MB",
    "file-types": "CSS, LESS, HTML, JavaScript",
    "description": "This is a theme from example data."
  },
  {
    "id": 300,
    "title": "Example Theme 3",
    "version": "1.0",
    "layouts": "Responsive, Fluid",
    "published": "January 29, 2013",
    "updated": "January 29, 2013",
    "size": "4 MB",
    "file-types": "CSS, LESS, HTML, JavaScript",
    "description": "This is a theme from example data."
  },
  {
    "id": 400,
    "title": "Example Theme 4",
    "version": "1.0",
    "layouts": "Responsive, Fluid",
    "published": "January 29, 2013",
    "updated": "January 29, 2013",
    "size": "4 MB",
    "file-types": "CSS, LESS, HTML, JavaScript",
    "description": "This is a theme from example data."
  },
  {
    "id": 500,
    "title": "Example Theme 5",
    "version": "1.0",
    "layouts": "Responsive, Fluid",
    "published": "January 29, 2013",
    "updated": "January 29, 2013",
    "size": "4 MB",
    "file-types": "CSS, LESS, HTML, JavaScript",
    "description": "This is a theme from example data."
  },
  {
    "id": 600,
    "title": "Example Theme 6",
    "version": "1.0",
    "layouts": "Responsive, Fluid",
    "published": "January 29, 2013",
    "updated": "January 29, 2013",
    "size": "4 MB",
    "file-types": "CSS, LESS, HTML, JavaScript",
    "description": "This is a theme from example data."
  }
]